animask/__init__.py
animask/__version__.py
animask/core.py
animask/utils.py
animask-0.0.1.dist-info/LICENSE
animask-0.0.1.dist-info/METADATA
animask-0.0.1.dist-info/WHEEL
animask-0.0.1.dist-info/top_level.txt
animask-0.0.1.dist-info/RECORD
