Metadata-Version: 2.1
Name: animask
Version: 0.0.1
Summary: Visualization of the predictions of the network during training.
Home-page: https://github.com/sankovalev/animask
Author: Alexander Kovalev
Author-email: sankovalev@gmail.com
License: MIT
Platform: UNKNOWN
Classifier: License :: OSI Approved :: MIT License
Classifier: Programming Language :: Python
Classifier: Programming Language :: Python :: 3
Requires-Python: >=3.0.0
Requires-Dist: numpy (>=1.16.3)
Requires-Dist: imageio (>=2.4.1)
Requires-Dist: opencv-python (>=4.1.0.*)
Requires-Dist: pygifsicle (>=1.0.*)
Provides-Extra: test
Requires-Dist: pytest ; extra == 'test'
